coco/__init__.py
coco/async_api.py
coco/coco.py
coco/config_models.py
coco/sync.py
coco/ccml/__init__.py
coco/ccml/consts.py
coco/ccml/converter.py
coco/ccml/parse.py
coco_sdk-0.1.13.dist-info/LICENSE
coco_sdk-0.1.13.dist-info/METADATA
coco_sdk-0.1.13.dist-info/WHEEL
coco_sdk-0.1.13.dist-info/top_level.txt
coco_sdk-0.1.13.dist-info/RECORD
