Metadata-Version: 2.1
Name: coco-sdk
Version: 0.1.13
Summary: CoCo(Conversational Components) SDK for building modular chatbots
Home-page: https://github.com/conversationalcomponents/coco-sdk-py
Author: Chen Buskilla
Author-email: chen@buskilla.com
License: MIT
Platform: UNKNOWN
Classifier: Development Status :: 2 - Pre-Alpha
Classifier: Intended Audience :: Developers
Classifier: Intended Audience :: Education
Classifier: Intended Audience :: Science/Research
Classifier: License :: OSI Approved :: MIT License
Classifier: Programming Language :: Python :: 3
Classifier: Topic :: Software Development :: Libraries
Classifier: Topic :: Software Development :: Libraries :: Python Modules
Requires-Python: >=3.6
Requires-Dist: requests
Requires-Dist: pygments
Requires-Dist: pydantic
Requires-Dist: lxml
Provides-Extra: async
Requires-Dist: httpx ; extra == 'async'
